README.md
setup.py
threadedreturn/__init__.py
threadedreturn/threadedreturn.py
threadedreturn.egg-info/PKG-INFO
threadedreturn.egg-info/SOURCES.txt
threadedreturn.egg-info/dependency_links.txt
threadedreturn.egg-info/top_level.txt