Metadata-Version: 2.1
Name: threadedreturn
Version: 1.0.1
Summary: Use threads with return values
Home-page: UNKNOWN
License: UNKNOWN
Keywords: threads,threading,concurrency
Platform: UNKNOWN
